[
{
	"uri": "https://alejandrocoria.games/es/",
	"title": "Alejandro Coria Games",
	"tags": [],
	"categories": [],
	"series": [],
	"description": "",
	"content": ""
},
{
	"uri": "https://alejandrocoria.games/es/trademark/",
	"title": "Aviso Legal Sobre Marcas Comerciales",
	"tags": [],
	"categories": [],
	"series": [],
	"description": "Uso de marca comercial y logo en la página.",
	"content": "Todos los nombre de productos, logotipos y marcas son propiedad de sus respectivos dueños. Todos los nombres de empresas, productos y servicios utilizados en este sitio web son solo para fines de identificación. El uso de estos nombres, logotipos y marcas no implica aprobación.\nGoogle Play y el logotipo de Google Play son marcas comerciales de Google LLC.\nGitHub y el logotipo de GitHub son marcas comerciales de GitHub, Inc.\nitch.io y el logotipo de itch.io son marcas comerciales de Itch Corp.\nKongregate y los logotipos de Kongregate son marcas comerciales de Kongregate Inc.\nLinkedIn y el logotipo de LinkedIn son marcas comerciales de LinkedIn Corporation.\nEl nombre y logotipo de Stack Exchange son marcas comerciales de Stack Exchange Inc.\nEl nombre y logotipo de Stack Overflow son marcas comerciales de Stack Exchange Inc.\nCurseForge y el logotipo de CurseForge son marcas comerciales de Twitch Interactive, Inc.\nTwitter y el logotipo de Twitter son marcas comerciales de Twitter, Inc.\n"
},
{
	"uri": "https://alejandrocoria.games/es/about/",
	"title": "Sobre mi",
	"tags": [],
	"categories": [],
	"series": [],
	"description": "Alejandro Coria Games. Mi página...",
	"content": "Soy un desarrollador de videojuegos independientes. Me gusta programar en C++, usar Godot y estoy empezando a crear mis primeros mods de Minecraft.\nSi te gusta mucho lo que hago, considera dar una donación :)\n"
},
{
	"uri": "https://alejandrocoria.games/es/tags/",
	"title": "Tags",
	"tags": [],
	"categories": [],
	"series": [],
	"description": "",
	"content": ""
}]